[
  {
    "constant": true,
    "inputs": [
      {
        "name": "_pool",
        "type": "address"
      },
      {
        "name": "_delegator",
        "type": "address"
      }
    ],
    "name": "poolDelegatorIndex",
    "outputs": [
      {
        "name": "",
        "type": "uint256"
      }
    ],
    "payable": false,
    "stateMutability": "view",
    "type": "function"
  },
  {
    "constant": true,
    "inputs": [
      {
        "name": "_pool",
        "type": "address"
      },
      {
        "name": "_staker",
        "type": "address"
      },
      {
        "name": "_stakingEpoch",
        "type": "uint256"
      }
    ],
    "name": "stakeAmountByEpoch",
    "outputs": [
      {
        "name": "",
        "type": "uint256"
      }
    ],
    "payable": false,
    "stateMutability": "view",
    "type": "function"
  },
  {
    "constant": true,
    "inputs": [],
    "name": "initiateChangeAllowed",
    "outputs": [
      {
        "name": "",
        "type": "bool"
      }
    ],
    "payable": false,
    "stateMutability": "view",
    "type": "function"
  },
  {
    "constant": false,
    "inputs": [
      {
        "name": "_erc20TokenContract",
        "type": "address"
      }
    ],
    "name": "setErc20TokenContract",
    "outputs": [],
    "payable": false,
    "stateMutability": "nonpayable",
    "type": "function"
  },
  {
    "constant": false,
    "inputs": [
      {
        "name": "_fromPool",
        "type": "address"
      },
      {
        "name": "_toPool",
        "type": "address"
      },
      {
        "name": "_amount",
        "type": "uint256"
      }
    ],
    "name": "moveStake",
    "outputs": [],
    "payable": false,
    "stateMutability": "nonpayable",
    "type": "function"
  },
  {
    "constant": false,
    "inputs": [
      {
        "name": "_minStake",
        "type": "uint256"
      }
    ],
    "name": "setDelegatorMinStake",
    "outputs": [],
    "payable": false,
    "stateMutability": "nonpayable",
    "type": "function"
  },
  {
    "constant": true,
    "inputs": [
      {
        "name": "_who",
        "type": "address"
      }
    ],
    "name": "isValidatorOnPreviousEpoch",
    "outputs": [
      {
        "name": "",
        "type": "bool"
      }
    ],
    "payable": false,
    "stateMutability": "view",
    "type": "function"
  },
  {
    "constant": true,
    "inputs": [],
    "name": "emitInitiateChangeCallable",
    "outputs": [
      {
        "name": "",
        "type": "bool"
      }
    ],
    "payable": false,
    "stateMutability": "view",
    "type": "function"
  },
  {
    "constant": false,
    "inputs": [],
    "name": "removePool",
    "outputs": [],
    "payable": false,
    "stateMutability": "nonpayable",
    "type": "function"
  },
  {
    "constant": false,
    "inputs": [
      {
        "name": "_minStake",
        "type": "uint256"
      }
    ],
    "name": "setCandidateMinStake",
    "outputs": [],
    "payable": false,
    "stateMutability": "nonpayable",
    "type": "function"
  },
  {
    "constant": true,
    "inputs": [
      {
        "name": "_pool",
        "type": "address"
      }
    ],
    "name": "stakeAmountTotal",
    "outputs": [
      {
        "name": "",
        "type": "uint256"
      }
    ],
    "payable": false,
    "stateMutability": "view",
    "type": "function"
  },
  {
    "constant": true,
    "inputs": [],
    "name": "blockRewardContract",
    "outputs": [
      {
        "name": "",
        "type": "address"
      }
    ],
    "payable": false,
    "stateMutability": "view",
    "type": "function"
  },
  {
    "constant": true,
    "inputs": [
      {
        "name": "_who",
        "type": "address"
      }
    ],
    "name": "bannedUntil",
    "outputs": [
      {
        "name": "",
        "type": "uint256"
      }
    ],
    "payable": false,
    "stateMutability": "view",
    "type": "function"
  },
  {
    "constant": true,
    "inputs": [
      {
        "name": "_who",
        "type": "address"
      }
    ],
    "name": "poolInactiveIndex",
    "outputs": [
      {
        "name": "",
        "type": "uint256"
      }
    ],
    "payable": false,
    "stateMutability": "view",
    "type": "function"
  },
  {
    "constant": true,
    "inputs": [],
    "name": "getPools",
    "outputs": [
      {
        "name": "",
        "type": "address[]"
      }
    ],
    "payable": false,
    "stateMutability": "view",
    "type": "function"
  },
  {
    "constant": true,
    "inputs": [],
    "name": "getQueueValidators",
    "outputs": [
      {
        "name": "",
        "type": "address[]"
      },
      {
        "name": "",
        "type": "bool"
      }
    ],
    "payable": false,
    "stateMutability": "view",
    "type": "function"
  },
  {
    "constant": true,
    "inputs": [
      {
        "name": "_pool",
        "type": "address"
      },
      {
        "name": "_staker",
        "type": "address"
      }
    ],
    "name": "maxWithdrawAllowed",
    "outputs": [
      {
        "name": "",
        "type": "uint256"
      }
    ],
    "payable": false,
    "stateMutability": "view",
    "type": "function"
  },
  {
    "constant": true,
    "inputs": [],
    "name": "MAX_VALIDATORS",
    "outputs": [
      {
        "name": "",
        "type": "uint256"
      }
    ],
    "payable": false,
    "stateMutability": "view",
    "type": "function"
  },
  {
    "constant": false,
    "inputs": [],
    "name": "finalizeChange",
    "outputs": [],
    "payable": false,
    "stateMutability": "nonpayable",
    "type": "function"
  },
  {
    "constant": true,
    "inputs": [],
    "name": "stakingEpoch",
    "outputs": [
      {
        "name": "",
        "type": "uint256"
      }
    ],
    "payable": false,
    "stateMutability": "view",
    "type": "function"
  },
  {
    "constant": true,
    "inputs": [],
    "name": "getDelegatorMinStake",
    "outputs": [
      {
        "name": "",
        "type": "uint256"
      }
    ],
    "payable": false,
    "stateMutability": "view",
    "type": "function"
  },
  {
    "constant": true,
    "inputs": [],
    "name": "getPreviousValidators",
    "outputs": [
      {
        "name": "",
        "type": "address[]"
      }
    ],
    "payable": false,
    "stateMutability": "view",
    "type": "function"
  },
  {
    "constant": true,
    "inputs": [],
    "name": "erc20TokenContract",
    "outputs": [
      {
        "name": "",
        "type": "address"
      }
    ],
    "payable": false,
    "stateMutability": "view",
    "type": "function"
  },
  {
    "constant": true,
    "inputs": [],
    "name": "getCandidateMinStake",
    "outputs": [
      {
        "name": "",
        "type": "uint256"
      }
    ],
    "payable": false,
    "stateMutability": "view",
    "type": "function"
  },
  {
    "constant": true,
    "inputs": [
      {
        "name": "_validator",
        "type": "address"
      }
    ],
    "name": "isReportValidatorValid",
    "outputs": [
      {
        "name": "",
        "type": "bool"
      }
    ],
    "payable": false,
    "stateMutability": "view",
    "type": "function"
  },
  {
    "constant": false,
    "inputs": [],
    "name": "emitInitiateChange",
    "outputs": [],
    "payable": false,
    "stateMutability": "nonpayable",
    "type": "function"
  },
  {
    "constant": true,
    "inputs": [
      {
        "name": "_validator",
        "type": "address"
      }
    ],
    "name": "validatorIndex",
    "outputs": [
      {
        "name": "",
        "type": "uint256"
      }
    ],
    "payable": false,
    "stateMutability": "view",
    "type": "function"
  },
  {
    "constant": true,
    "inputs": [
      {
        "name": "_pool",
        "type": "address"
      }
    ],
    "name": "poolDelegators",
    "outputs": [
      {
        "name": "",
        "type": "address[]"
      }
    ],
    "payable": false,
    "stateMutability": "view",
    "type": "function"
  },
  {
    "constant": true,
    "inputs": [
      {
        "name": "_pool",
        "type": "address"
      },
      {
        "name": "_staker",
        "type": "address"
      }
    ],
    "name": "stakeAmount",
    "outputs": [
      {
        "name": "",
        "type": "uint256"
      }
    ],
    "payable": false,
    "stateMutability": "view",
    "type": "function"
  },
  {
    "constant": true,
    "inputs": [
      {
        "name": "_who",
        "type": "address"
      }
    ],
    "name": "isPoolActive",
    "outputs": [
      {
        "name": "",
        "type": "bool"
      }
    ],
    "payable": false,
    "stateMutability": "view",
    "type": "function"
  },
  {
    "constant": true,
    "inputs": [
      {
        "name": "_validator",
        "type": "address"
      }
    ],
    "name": "isValidatorBanned",
    "outputs": [
      {
        "name": "",
        "type": "bool"
      }
    ],
    "payable": false,
    "stateMutability": "view",
    "type": "function"
  },
  {
    "constant": false,
    "inputs": [
      {
        "name": "_toPool",
        "type": "address"
      },
      {
        "name": "_amount",
        "type": "uint256"
      }
    ],
    "name": "stake",
    "outputs": [],
    "payable": false,
    "stateMutability": "nonpayable",
    "type": "function"
  },
  {
    "constant": true,
    "inputs": [
      {
        "name": "_who",
        "type": "address"
      }
    ],
    "name": "poolIndex",
    "outputs": [
      {
        "name": "",
        "type": "uint256"
      }
    ],
    "payable": false,
    "stateMutability": "view",
    "type": "function"
  },
  {
    "constant": true,
    "inputs": [
      {
        "name": "_who",
        "type": "address"
      }
    ],
    "name": "doesPoolExist",
    "outputs": [
      {
        "name": "",
        "type": "bool"
      }
    ],
    "payable": false,
    "stateMutability": "view",
    "type": "function"
  },
  {
    "constant": true,
    "inputs": [],
    "name": "getValidators",
    "outputs": [
      {
        "name": "",
        "type": "address[]"
      }
    ],
    "payable": false,
    "stateMutability": "view",
    "type": "function"
  },
  {
    "constant": true,
    "inputs": [],
    "name": "STAKE_UNIT",
    "outputs": [
      {
        "name": "",
        "type": "uint256"
      }
    ],
    "payable": false,
    "stateMutability": "view",
    "type": "function"
  },
  {
    "constant": true,
    "inputs": [],
    "name": "validatorSetApplyBlock",
    "outputs": [
      {
        "name": "",
        "type": "uint256"
      }
    ],
    "payable": false,
    "stateMutability": "view",
    "type": "function"
  },
  {
    "constant": false,
    "inputs": [
      {
        "name": "_pool",
        "type": "address"
      },
      {
        "name": "_staker",
        "type": "address[]"
      },
      {
        "name": "_stakingEpoch",
        "type": "uint256"
      }
    ],
    "name": "clearStakeHistory",
    "outputs": [],
    "payable": false,
    "stateMutability": "nonpayable",
    "type": "function"
  },
  {
    "constant": true,
    "inputs": [],
    "name": "randomContract",
    "outputs": [
      {
        "name": "",
        "type": "address"
      }
    ],
    "payable": false,
    "stateMutability": "view",
    "type": "function"
  },
  {
    "constant": true,
    "inputs": [],
    "name": "changeRequestCount",
    "outputs": [
      {
        "name": "",
        "type": "uint256"
      }
    ],
    "payable": false,
    "stateMutability": "view",
    "type": "function"
  },
  {
    "constant": true,
    "inputs": [],
    "name": "getPoolsInactive",
    "outputs": [
      {
        "name": "",
        "type": "address[]"
      }
    ],
    "payable": false,
    "stateMutability": "view",
    "type": "function"
  },
  {
    "constant": true,
    "inputs": [],
    "name": "getPendingValidators",
    "outputs": [
      {
        "name": "",
        "type": "address[]"
      }
    ],
    "payable": false,
    "stateMutability": "view",
    "type": "function"
  },
  {
    "constant": true,
    "inputs": [],
    "name": "MAX_CANDIDATES",
    "outputs": [
      {
        "name": "",
        "type": "uint256"
      }
    ],
    "payable": false,
    "stateMutability": "view",
    "type": "function"
  },
  {
    "constant": false,
    "inputs": [
      {
        "name": "_fromPool",
        "type": "address"
      },
      {
        "name": "_amount",
        "type": "uint256"
      }
    ],
    "name": "withdraw",
    "outputs": [],
    "payable": false,
    "stateMutability": "nonpayable",
    "type": "function"
  },
  {
    "constant": true,
    "inputs": [
      {
        "name": "_who",
        "type": "address"
      }
    ],
    "name": "isValidator",
    "outputs": [
      {
        "name": "",
        "type": "bool"
      }
    ],
    "payable": false,
    "stateMutability": "view",
    "type": "function"
  },
  {
    "anonymous": false,
    "inputs": [
      {
        "indexed": false,
        "name": "reportingValidator",
        "type": "address"
      },
      {
        "indexed": false,
        "name": "maliciousValidator",
        "type": "address"
      },
      {
        "indexed": false,
        "name": "blockNumber",
        "type": "uint256"
      }
    ],
    "name": "ReportedMalicious",
    "type": "event"
  },
  {
    "anonymous": false,
    "inputs": [
      {
        "indexed": true,
        "name": "parentHash",
        "type": "bytes32"
      },
      {
        "indexed": false,
        "name": "newSet",
        "type": "address[]"
      }
    ],
    "name": "InitiateChange",
    "type": "event"
  },
  {
    "anonymous": false,
    "inputs": [
      {
        "indexed": true,
        "name": "toPool",
        "type": "address"
      },
      {
        "indexed": true,
        "name": "staker",
        "type": "address"
      },
      {
        "indexed": true,
        "name": "stakingEpoch",
        "type": "uint256"
      },
      {
        "indexed": false,
        "name": "amount",
        "type": "uint256"
      }
    ],
    "name": "Staked",
    "type": "event"
  },
  {
    "anonymous": false,
    "inputs": [
      {
        "indexed": false,
        "name": "fromPool",
        "type": "address"
      },
      {
        "indexed": true,
        "name": "toPool",
        "type": "address"
      },
      {
        "indexed": true,
        "name": "staker",
        "type": "address"
      },
      {
        "indexed": true,
        "name": "stakingEpoch",
        "type": "uint256"
      },
      {
        "indexed": false,
        "name": "amount",
        "type": "uint256"
      }
    ],
    "name": "StakeMoved",
    "type": "event"
  },
  {
    "anonymous": false,
    "inputs": [
      {
        "indexed": true,
        "name": "fromPool",
        "type": "address"
      },
      {
        "indexed": true,
        "name": "staker",
        "type": "address"
      },
      {
        "indexed": true,
        "name": "stakingEpoch",
        "type": "uint256"
      },
      {
        "indexed": false,
        "name": "amount",
        "type": "uint256"
      }
    ],
    "name": "Withdrawn",
    "type": "event"
  },
  {
    "constant": false,
    "inputs": [
      {
        "name": "_amount",
        "type": "uint256"
      }
    ],
    "name": "addPool",
    "outputs": [],
    "payable": false,
    "stateMutability": "nonpayable",
    "type": "function"
  },
  {
    "constant": false,
    "inputs": [
      {
        "name": "_blockRewardContract",
        "type": "address"
      },
      {
        "name": "_randomContract",
        "type": "address"
      },
      {
        "name": "_erc20TokenContract",
        "type": "address"
      },
      {
        "name": "_initialValidators",
        "type": "address[]"
      },
      {
        "name": "_delegatorMinStake",
        "type": "uint256"
      },
      {
        "name": "_candidateMinStake",
        "type": "uint256"
      },
      {
        "name": "_stakingEpochDuration",
        "type": "uint256"
      }
    ],
    "name": "initialize",
    "outputs": [],
    "payable": false,
    "stateMutability": "nonpayable",
    "type": "function"
  },
  {
    "constant": false,
    "inputs": [],
    "name": "newValidatorSet",
    "outputs": [],
    "payable": false,
    "stateMutability": "nonpayable",
    "type": "function"
  },
  {
    "constant": false,
    "inputs": [
      {
        "name": "_validator",
        "type": "address"
      }
    ],
    "name": "removeMaliciousValidator",
    "outputs": [],
    "payable": false,
    "stateMutability": "nonpayable",
    "type": "function"
  },
  {
    "constant": false,
    "inputs": [
      {
        "name": "",
        "type": "address"
      },
      {
        "name": "",
        "type": "uint256"
      }
    ],
    "name": "reportBenign",
    "outputs": [],
    "payable": false,
    "stateMutability": "nonpayable",
    "type": "function"
  },
  {
    "constant": false,
    "inputs": [
      {
        "name": "_maliciousValidator",
        "type": "address"
      },
      {
        "name": "_blockNumber",
        "type": "uint256"
      },
      {
        "name": "",
        "type": "bytes"
      }
    ],
    "name": "reportMalicious",
    "outputs": [],
    "payable": false,
    "stateMutability": "nonpayable",
    "type": "function"
  },
  {
    "constant": true,
    "inputs": [
      {
        "name": "_validator",
        "type": "address"
      },
      {
        "name": "_blockNumber",
        "type": "uint256"
      }
    ],
    "name": "maliceReportedForBlock",
    "outputs": [
      {
        "name": "",
        "type": "address[]"
      }
    ],
    "payable": false,
    "stateMutability": "view",
    "type": "function"
  },
  {
    "constant": true,
    "inputs": [],
    "name": "stakeWithdrawDisallowPeriod",
    "outputs": [
      {
        "name": "",
        "type": "uint256"
      }
    ],
    "payable": false,
    "stateMutability": "view",
    "type": "function"
  },
  {
    "constant": true,
    "inputs": [],
    "name": "stakingEpochDuration",
    "outputs": [
      {
        "name": "",
        "type": "uint256"
      }
    ],
    "payable": false,
    "stateMutability": "view",
    "type": "function"
  },
  {
    "constant": true,
    "inputs": [],
    "name": "stakingEpochStartBlock",
    "outputs": [
      {
        "name": "",
        "type": "uint256"
      }
    ],
    "payable": false,
    "stateMutability": "view",
    "type": "function"
  }
]